bootstrapping_tools/__init__.py
bootstrapping_tools/abstract_series_bootstrapper.py
bootstrapping_tools/bootstrap_parametrizer.py
bootstrapping_tools/bootstrapping.py
bootstrapping_tools/n0_and_lambdas_intervals.py
bootstrapping_tools/resample_by_blocks.py
bootstrapping_tools-3.2.0.dist-info/LICENSE
bootstrapping_tools-3.2.0.dist-info/WHEEL
bootstrapping_tools-3.2.0.dist-info/METADATA
bootstrapping_tools-3.2.0.dist-info/RECORD
