Metadata-Version: 2.1
Name: bootstrapping_tools
Version: 3.2.0
Summary: GECI Tools for bootstrapping
Home-page: https://github.com/IslasGECI/bootstrapping_tools
Author: Ciencia de Datos • GECI
Author-email: ciencia.datos@islas.org.mx
Requires-Python: >=3
Classifier: License :: OSI Approved :: GNU General Public License v3 or later (GPLv3+)
Requires-Dist: numpy
Requires-Dist: pandas-stubs
Requires-Dist: pandas
Requires-Dist: scipy
Requires-Dist: tqdm
